jupyterlite_ai/__init__.py
jupyterlite_ai/_version.py
jupyterlite_ai-0.10.0.data/data/share/jupyter/labextensions/@jupyterlite/ai/package.json
jupyterlite_ai-0.10.0.data/data/share/jupyter/labextensions/@jupyterlite/ai/schemas/@jupyterlite/ai/package.json.orig
jupyterlite_ai-0.10.0.data/data/share/jupyter/labextensions/@jupyterlite/ai/schemas/@jupyterlite/ai/settings-model.json
jupyterlite_ai-0.10.0.data/data/share/jupyter/labextensions/@jupyterlite/ai/static/116.5aa31e6f41f681ffe176.js
jupyterlite_ai-0.10.0.data/data/share/jupyter/labextensions/@jupyterlite/ai/static/155.d5bf7ae6d55452a6819b.js
jupyterlite_ai-0.10.0.data/data/share/jupyter/labextensions/@jupyterlite/ai/static/195.2a52896581f32669a80b.js
jupyterlite_ai-0.10.0.data/data/share/jupyter/labextensions/@jupyterlite/ai/static/313.7364304c899b918860da.js
jupyterlite_ai-0.10.0.data/data/share/jupyter/labextensions/@jupyterlite/ai/static/482.7d44d1b87a9eb0c8d565.js
jupyterlite_ai-0.10.0.data/data/share/jupyter/labextensions/@jupyterlite/ai/static/529.600d1aebb2de2d73fecb.js
jupyterlite_ai-0.10.0.data/data/share/jupyter/labextensions/@jupyterlite/ai/static/529.600d1aebb2de2d73fecb.js.LICENSE.txt
jupyterlite_ai-0.10.0.data/data/share/jupyter/labextensions/@jupyterlite/ai/static/634.aef732b72a1430420948.js
jupyterlite_ai-0.10.0.data/data/share/jupyter/labextensions/@jupyterlite/ai/static/669.2a2cc1fd753ba82f201b.js
jupyterlite_ai-0.10.0.data/data/share/jupyter/labextensions/@jupyterlite/ai/static/694.7364304c899b918860da.js
jupyterlite_ai-0.10.0.data/data/share/jupyter/labextensions/@jupyterlite/ai/static/709.7578153f9eed366ee430.js
jupyterlite_ai-0.10.0.data/data/share/jupyter/labextensions/@jupyterlite/ai/static/709.7578153f9eed366ee430.js.LICENSE.txt
jupyterlite_ai-0.10.0.data/data/share/jupyter/labextensions/@jupyterlite/ai/static/721.dbe55a93e78524a45849.js
jupyterlite_ai-0.10.0.data/data/share/jupyter/labextensions/@jupyterlite/ai/static/728.0f7b61353675ad5914f9.js
jupyterlite_ai-0.10.0.dist-info/METADATA
jupyterlite_ai-0.10.0.dist-info/WHEEL
jupyterlite_ai-0.10.0.dist-info/licenses/LICENSE
jupyterlite_ai-0.10.0.dist-info/RECORD
