Metadata-Version: 2.4
Name: jupyterlite_ai
Version: 0.10.0
Dynamic: Keywords
Summary: AI code completions and chat for JupyterLite
Project-URL: Homepage, https://github.com/jupyterlite/ai
Project-URL: Bug Tracker, https://github.com/jupyterlite/ai/issues
Project-URL: Repository, https://github.com/jupyterlite/ai.git
Author: JupyterLite Contributors
License: BSD 3-Clause License
License-File: LICENSE
Classifier: Framework :: Jupyter
Classifier: Framework :: Jupyter :: JupyterLab
Classifier: Framework :: Jupyter :: JupyterLab :: 4
Classifier: Framework :: Jupyter :: JupyterLab :: Extensions
Classifier: Framework :: Jupyter :: JupyterLab :: Extensions :: Prebuilt
Classifier: License :: OSI Approved :: BSD License
Classifier: Programming Language :: Python
Classifier: Programming Language :: Python :: 3
Classifier: Programming Language :: Python :: 3.9
Classifier: Programming Language :: Python :: 3.10
Classifier: Programming Language :: Python :: 3.11
Classifier: Programming Language :: Python :: 3.12
Classifier: Programming Language :: Python :: 3.13
Requires-Python: >=3.9
Requires-Dist: jupyter-secrets-manager<0.5,>=0.4
Requires-Dist: jupyterlab-diff<0.7,>=0.6.0
Provides-Extra: docs
Requires-Dist: jupyter-book; extra == 'docs'
Provides-Extra: jupyter
Requires-Dist: jupyterlab>=4.4.0; extra == 'jupyter'
Requires-Dist: jupyterlite>=0.6.0a0; extra == 'jupyter'
Requires-Dist: notebook>=7.4.0; extra == 'jupyter'
Provides-Extra: test
Requires-Dist: fastmcp<3,>=2.12.4; extra == 'test'
Requires-Dist: starlette<0.49,>=0.48.0; extra == 'test'
